README
setup.py
serve.me.egg-info/PKG-INFO
serve.me.egg-info/SOURCES.txt
serve.me.egg-info/dependency_links.txt
serve.me.egg-info/entry_points.txt
serve.me.egg-info/requires.txt
serve.me.egg-info/top_level.txt
serveme/__init__.py
serveme/app.py