Metadata-Version: 1.0
Name: serve.me
Version: 0.1.0
Summary: serve.me is a quick and dirty webserver to serve the current folder
Home-page: http://github.com/heynemann/serve.me
Author: Bernardo Heynemann
Author-email: heynemann@gmail.com
License: MIT
Keywords: web server static files
Platform: UNKNOWN
Classifier: Development Status :: 4 - Beta
Classifier: Intended Audience :: Developers
Classifier: License :: OSI Approved :: MIT License
Classifier: Natural Language :: English
Classifier: Operating System :: MacOS
Classifier: Operating System :: POSIX :: Linux
Classifier: Programming Language :: Python :: 2.6
Classifier: Topic :: Internet :: WWW/HTTP :: Dynamic Content
